eaglet/__init__.py
tests/__init__.py
eaglet-0.0.2.dist-info/LICENSE
eaglet-0.0.2.dist-info/METADATA
eaglet-0.0.2.dist-info/WHEEL
eaglet-0.0.2.dist-info/top_level.txt
eaglet-0.0.2.dist-info/RECORD
