Metadata-Version: 2.1
Name: eaglet
Version: 0.0.2
Summary: Time Series Forecasting Toolkits
Home-page: https://github.com/Mtax/eaglet
Author: Eminjan Turamat
Author-email: yiminjiang@ainnovation.com
License: UNKNOWN
Platform: UNKNOWN
Classifier: Programming Language :: Python :: 3
Classifier: License :: OSI Approved :: MIT License
Classifier: Operating System :: OS Independent
Requires-Python: >=3.6
